{
    "11000": {
        "random": [],
        "softmax_entropy": [
            0.6571000218391418,
            0.6582000255584717
        ],
        "NUC": [],
        "NUC Tr": [],
        "MC_drop": {
            "SE": [],
            "MI": []
        },
        "Ensembles": {
            "BaggingEns": {
                "SE": [],
                "MI": []
            },
            "DataAugmentationEns": {
                "SE": [],
                "MI": []
            }
        }
    },
    "12000": {
        "random": [],
        "softmax_entropy": [
            0.6633999943733215
        ],
        "NUC": [],
        "NUC Tr": [],
        "MC_drop": {
            "SE": [],
            "MI": []
        },
        "Ensembles": {
            "BaggingEns": {
                "SE": [],
                "MI": []
            },
            "DataAugmentationEns": {
                "SE": [],
                "MI": []
            }
        }
    },
    "13000": {
        "random": [],
        "softmax_entropy": [
            0.671500027179718
        ],
        "NUC": [],
        "NUC Tr": [],
        "MC_drop": {
            "SE": [],
            "MI": []
        },
        "Ensembles": {
            "BaggingEns": {
                "SE": [],
                "MI": []
            },
            "DataAugmentationEns": {
                "SE": [],
                "MI": []
            }
        }
    },
    "14000": {
        "random": [],
        "softmax_entropy": [
            0.6794999837875366
        ],
        "NUC": [],
        "NUC Tr": [],
        "MC_drop": {
            "SE": [],
            "MI": []
        },
        "Ensembles": {
            "BaggingEns": {
                "SE": [],
                "MI": []
            },
            "DataAugmentationEns": {
                "SE": [],
                "MI": []
            }
        }
    },
    "15000": {
        "random": [],
        "softmax_entropy": [
            0.6798999905586243
        ],
        "NUC": [],
        "NUC Tr": [],
        "MC_drop": {
            "SE": [],
            "MI": []
        },
        "Ensembles": {
            "BaggingEns": {
                "SE": [],
                "MI": []
            },
            "DataAugmentationEns": {
                "SE": [],
                "MI": []
            }
        }
    },
    "16000": {
        "random": [],
        "softmax_entropy": [
            0.6935999989509583
        ],
        "NUC": [],
        "NUC Tr": [],
        "MC_drop": {
            "SE": [],
            "MI": []
        },
        "Ensembles": {
            "BaggingEns": {
                "SE": [],
                "MI": []
            },
            "DataAugmentationEns": {
                "SE": [],
                "MI": []
            }
        }
    },
    "17000": {
        "random": [],
        "softmax_entropy": [
            0.6804999709129333
        ],
        "NUC": [],
        "NUC Tr": [],
        "MC_drop": {
            "SE": [],
            "MI": []
        },
        "Ensembles": {
            "BaggingEns": {
                "SE": [],
                "MI": []
            },
            "DataAugmentationEns": {
                "SE": [],
                "MI": []
            }
        }
    },
    "18000": {
        "random": [],
        "softmax_entropy": [
            0.6942999958992004
        ],
        "NUC": [],
        "NUC Tr": [],
        "MC_drop": {
            "SE": [],
            "MI": []
        },
        "Ensembles": {
            "BaggingEns": {
                "SE": [],
                "MI": []
            },
            "DataAugmentationEns": {
                "SE": [],
                "MI": []
            }
        }
    },
    "19000": {
        "random": [],
        "softmax_entropy": [
            0.6977999806404114
        ],
        "NUC": [],
        "NUC Tr": [],
        "MC_drop": {
            "SE": [],
            "MI": []
        },
        "Ensembles": {
            "BaggingEns": {
                "SE": [],
                "MI": []
            },
            "DataAugmentationEns": {
                "SE": [],
                "MI": []
            }
        }
    },
    "20000": {
        "random": [],
        "softmax_entropy": [
            0.6862999796867371
        ],
        "NUC": [],
        "NUC Tr": [],
        "MC_drop": {
            "SE": [],
            "MI": []
        },
        "Ensembles": {
            "BaggingEns": {
                "SE": [],
                "MI": []
            },
            "DataAugmentationEns": {
                "SE": [],
                "MI": []
            }
        }
    }
}